{
    "zhuanti":[
        {
            "_id":1,
            "img":"img/pika.jpg",
            "name":"产品经理",
            "sloen":"点线面体的产品思维",
            "focus":true
        },
        {
            "_id":2,
            "img":"img/pika.jpg",
            "name":"@it互联网",
            "sloen":"如和写出优秀的错误提示",
            "focus":true
        },
        {
            "_id":3,
            "img":"img/pika.jpg",
            "name":"Nvemore",
            "sloen":"呵呵呵呵呵呵",
            "focus":true
        },
        {
            "_id":4,
            "img":"img/pika.jpg",
            "name":"简书官方",
            "sloen":"发文章，换新装",
            "focus":true
        }
    ],
    "wenji":[
        {
            "_id":1,
            "img":"img/book2.jpg",
            "name":"原型设计分享",
            "sloen":"【原型设计】如何实现淘宝5星好评",
            "focus":true
        },
        {
            "_id":2,
            "img":"img/book2.jpg",
            "name":"互联网产品设计心得",
            "sloen":"看完这篇文章，策划线下活动不迷茫",
            "focus":true
        }
    ],
    "lianzai":[
        {
            "_id":1,
            "img":"img/book.jpg",
            "title":"区块链社会学",
            "name":"培文培育",
            "number":132,
            "focus":752
        },
        {
            "_id":2,
            "img":"img/book.jpg",
            "title":"语文",
            "name":"社会主义",
            "number":132,
            "focus":666
        }
    ]
}